autogqlschema/__init__.py
autogqlschema/_directive.py
autogqlschema/_extension.py
autogqlschema/_objects.py
autogqlschema/_parser.py
autogqlschema/_renderer.py
autogqlschema/_templates/__init__.py
autogqlschema/_templates/directive.md.jinja
autogqlschema/_templates/enum.md.jinja
autogqlschema/_templates/enum_value.md.jinja
autogqlschema/_templates/input.md.jinja
autogqlschema/_templates/input_field.md.jinja
autogqlschema/_templates/interface.md.jinja
autogqlschema/_templates/interface_field.md.jinja
autogqlschema/_templates/scalar.md.jinja
autogqlschema/_templates/schema.md.jinja
autogqlschema/_templates/type.md.jinja
autogqlschema/_templates/type_field.md.jinja
autogqlschema/_templates/union.md.jinja
autogqlschema-1.0.0.dist-info/LICENSE.rst
autogqlschema-1.0.0.dist-info/WHEEL
autogqlschema-1.0.0.dist-info/METADATA
autogqlschema-1.0.0.dist-info/RECORD
