Metadata-Version: 2.3
Name: autogqlschema
Version: 1.0.0
Summary: A Sphinx extension for automatically documenting GraphQL schemas.
Author-email: Ashley Whetter <ashley@awhetter.co.uk>
Requires-Python: >=3.9
Classifier: Development Status :: 5 - Production/Stable
Classifier: Environment :: Plugins
Classifier: Framework :: Sphinx :: Extension
Classifier: Intended Audience :: Developers
Classifier: License :: OSI Approved :: MIT License
Classifier: Natural Language :: English
Classifier: Programming Language :: Python
Classifier: Programming Language :: Python :: 3
Classifier: Programming Language :: Python :: 3.9
Classifier: Programming Language :: Python :: 3.10
Classifier: Programming Language :: Python :: 3.11
Classifier: Programming Language :: Python :: 3.12
Classifier: Programming Language :: Python :: 3.13
Classifier: Topic :: Documentation :: Sphinx
Requires-Dist: graphqldomain>=0.2.0
Requires-Dist: myst-parser>=0.16.0
Requires-Dist: sphinx>=4.0
Requires-Dist: typing-extensions>=4.0
Project-URL: Documentation, https://autogqlschema.readthedocs.org
Project-URL: Source, https://github.com/AWhetter/autogqlschema
